logger.py
logger/__init__.py
logger/main.py
alertnow_python-1.1.3.dist-info/LICENSE.txt
alertnow_python-1.1.3.dist-info/METADATA
alertnow_python-1.1.3.dist-info/WHEEL
alertnow_python-1.1.3.dist-info/top_level.txt
alertnow_python-1.1.3.dist-info/RECORD
